Metadata-Version: 1.0
Name: asdasdcolbytest
Version: 0.0.1
Summary: The funniest joke in the world
Home-page: http://github.com/
Author: zzz
Author-email: zzz@example.com
License: MIT
Platform: UNKNOWN
